K2SC-1.0.2.2.data/scripts/k2ginfo
K2SC-1.0.2.2.data/scripts/k2mastify
K2SC-1.0.2.2.data/scripts/k2plot
K2SC-1.0.2.2.data/scripts/k2sc
k2sc/__init__.py
k2sc/cdpp.py
k2sc/core.py
k2sc/de.py
k2sc/detrender.py
k2sc/dtdata.py
k2sc/gp.py
k2sc/k2data.py
k2sc/k2io.py
k2sc/k2scfile.py
k2sc/kernels.py
k2sc/ls.py
k2sc/priors.py
k2sc/segdetrender.py
k2sc/standalone.py
k2sc/utils.py
K2SC-1.0.2.2.dist-info/LICENSE
K2SC-1.0.2.2.dist-info/METADATA
K2SC-1.0.2.2.dist-info/WHEEL
K2SC-1.0.2.2.dist-info/top_level.txt
K2SC-1.0.2.2.dist-info/RECORD
