Metadata-Version: 2.1
Name: K2SC
Version: 1.0.2.2
Summary: K2 light curve detrending with Gaussian Processes.
Home-page: https://github.com/OxES/k2sc
Author: Suzanne Aigrain
Author-email: suzanne.aigrain@physics.ox.ac.uk
License: GPLv3
Classifier: Topic :: Scientific/Engineering
Classifier: Intended Audience :: Science/Research
Classifier: Intended Audience :: Developers
Classifier: Development Status :: 4 - Beta
Classifier: License :: OSI Approved :: GNU General Public License v3 (GPLv3)
Classifier: Operating System :: OS Independent
Classifier: Programming Language :: Python
License-File: LICENSE
Requires-Dist: numpy
Requires-Dist: astropy
Requires-Dist: scipy
Requires-Dist: george>=0.3
